envfile.py
envfile-1.0.dist-info/DESCRIPTION.rst
envfile-1.0.dist-info/entry_points.txt
envfile-1.0.dist-info/METADATA
envfile-1.0.dist-info/metadata.json
envfile-1.0.dist-info/RECORD
envfile-1.0.dist-info/top_level.txt
envfile-1.0.dist-info/WHEEL
